PrivateModelArchitectures/__init__.py
PrivateModelArchitectures/classification/ResNet.py
PrivateModelArchitectures/classification/SmoothNet.py
PrivateModelArchitectures/classification/__init__.py
PrivateModelArchitectures/segmentation/LinkNet.py
PrivateModelArchitectures/segmentation/UNet.py
PrivateModelArchitectures/segmentation/__init__.py
PrivateModelArchitectures-0.1.1.dist-info/METADATA
PrivateModelArchitectures-0.1.1.dist-info/WHEEL
PrivateModelArchitectures-0.1.1.dist-info/top_level.txt
PrivateModelArchitectures-0.1.1.dist-info/RECORD
